pasjonsfrukt/__init__.py
pasjonsfrukt/api.py
pasjonsfrukt/async_cli.py
pasjonsfrukt/cli.py
pasjonsfrukt/config.py
pasjonsfrukt/logging_utils.py
pasjonsfrukt/main.py
pasjonsfrukt-0.2.6.dist-info/LICENSE
pasjonsfrukt-0.2.6.dist-info/METADATA
pasjonsfrukt-0.2.6.dist-info/WHEEL
pasjonsfrukt-0.2.6.dist-info/entry_points.txt
pasjonsfrukt-0.2.6.dist-info/RECORD
