Metadata-Version: 2.3
Name: pasjonsfrukt
Version: 0.2.6
Summary: Scrape PodMe podcast streams to mp3 and host with RSS feed
Author: Mathias Oterhals Myklebust
Author-email: mathias@oterbust.no
Requires-Python: >=3.11,<4.0
Classifier: Development Status :: 4 - Beta
Classifier: Intended Audience :: Developers
Classifier: License :: OSI Approved :: MIT License
Classifier: Operating System :: OS Independent
Classifier: Programming Language :: Python :: 3
Classifier: Programming Language :: Python :: 3.11
Classifier: Programming Language :: Python :: 3.12
Classifier: Programming Language :: Python :: 3.13
Classifier: Programming Language :: Python :: 3.10
Requires-Dist: asyncer (==0.0.8)
Requires-Dist: dataclass-wizard[yaml] (==0.35.0)
Requires-Dist: fastapi (==0.115.8)
Requires-Dist: podme-api (==1.4.2)
Requires-Dist: rfeed (>=1.1.1,<2.0.0)
Requires-Dist: typer (==0.15.1)
Requires-Dist: uvicorn (==0.34.0)
Project-URL: Bug Tracker, https://github.com/mathiazom/pasjonsfrukt/issues
Project-URL: Homepage, https://github.com/mathiazom/pasjonsfrukt
Project-URL: Repository, https://github.com/mathiazom/pasjonsfrukt
